hijacknet/__about__.py
hijacknet/__init__.py
hijacknet-0.0.2.dist-info/METADATA
hijacknet-0.0.2.dist-info/WHEEL
hijacknet-0.0.2.dist-info/licenses/LICENSE.txt
hijacknet-0.0.2.dist-info/RECORD
