Metadata-Version: 2.1
Name: hijacknet
Version: 0.0.2
Summary: Simple line-based networking
Project-URL: Documentation, https://github.com/Cyclic3/hijacknet#readme
Project-URL: Issues, https://github.com/Cyclic3/hijacknet/issues
Project-URL: Source, https://github.com/Cyclic3/hijacknet
Author-email: Cyclic3 <cyclic3.git@gmail.com>
License-Expression: MIT
License-File: LICENSE.txt
Classifier: Development Status :: 4 - Beta
Classifier: Programming Language :: Python
Classifier: Programming Language :: Python :: 3.7
Classifier: Programming Language :: Python :: 3.8
Classifier: Programming Language :: Python :: 3.9
Classifier: Programming Language :: Python :: 3.10
Classifier: Programming Language :: Python :: 3.11
Classifier: Programming Language :: Python :: Implementation :: CPython
Classifier: Programming Language :: Python :: Implementation :: PyPy
Requires-Python: >=3.7
